docassemble/EFSPIntegration/__init__.py
docassemble/EFSPIntegration/conversions.py
docassemble/EFSPIntegration/efm_client.py
docassemble/EFSPIntegration/interview_logic.py
docassemble/EFSPIntegration/py.typed
docassemble/EFSPIntegration/py_efsp_client.py
docassemble/EFSPIntegration/requirements.txt
docassemble/EFSPIntegration/data/questions/admin_interview.yml
docassemble/EFSPIntegration/data/questions/any_filing_interview.yml
docassemble/EFSPIntegration/data/questions/case_search.yml
docassemble/EFSPIntegration/data/questions/codes_interview.yml
docassemble/EFSPIntegration/data/questions/efiling_integration.yml
docassemble/EFSPIntegration/data/questions/login_qs.yml
docassemble/EFSPIntegration/data/questions/logs_interview.yml
docassemble/EFSPIntegration/data/questions/minimal_interview.yml
docassemble/EFSPIntegration/data/questions/toga_payments.yml
docassemble/EFSPIntegration/data/questions/toga_payments_interview.yml
docassemble/EFSPIntegration/data/questions/unauthenticated_actions.yml
docassemble/EFSPIntegration/data/questions/unauthenticated_interview.yml
docassemble/EFSPIntegration/data/sources/README.md
docassemble/EFSPIntegration/data/sources/admin_interview.feature
docassemble/EFSPIntegration/data/sources/any_filing_interview.feature
docassemble/EFSPIntegration/data/sources/example_upload.pdf
docassemble/EFSPIntegration/data/sources/unauthenticated_interview.feature
docassemble/EFSPIntegration/data/static/Ajax-loader.gif
docassemble/EFSPIntegration/data/static/README.md
docassemble/EFSPIntegration/data/templates/README.md
docassemble/EFSPIntegration/test/__init__.py
docassemble/EFSPIntegration/test/opening_affidavit_adams.json
docassemble/EFSPIntegration/test/peoria_to_cr.json
docassemble/EFSPIntegration/test/temp2.json
docassemble/EFSPIntegration/test/test_conversions.py
docassemble/EFSPIntegration/test/test_interview_functions.py
docassemble/EFSPIntegration/test/test_proxy_conn.py
docassemble/EFSPIntegration/test/vars.json
docassemble_efspintegration-1.7.3.dist-info/licenses/LICENSE
docassemble_efspintegration-1.7.3.dist-info/METADATA
docassemble_efspintegration-1.7.3.dist-info/WHEEL
docassemble_efspintegration-1.7.3.dist-info/top_level.txt
docassemble_efspintegration-1.7.3.dist-info/RECORD
