Metadata-Version: 2.4
Name: docassemble.EFSPIntegration
Version: 1.7.3
Home-page: https://github.com/SuffolkLITLab/docassemble-EFSPIntegration
Author: Bryce Willey
Author-email: Bryce Willey <bryce.willey@suffolk.edu>
License-Expression: MIT
Project-URL: GitHub, https://github.com/SuffolkLITLab/docassemble-EFSPIntegration
Requires-Python: <3.13,>=3.10,>=3.12.3
License-File: LICENSE
Requires-Dist: docassemble.AssemblyLine>=3.5.0
Requires-Dist: docassemble.ALToolbox>=0.6.2
Requires-Dist: requests>2.25.1
Dynamic: author
Dynamic: home-page
Dynamic: license-file
